{
"type": "FeatureCollection",
"crs": { "type": "name", "properties": { "name": "urn:ogc:def:crs:OGC:1.3:CRS84" } },
"features": [
{ "type": "Feature", "properties": { "ID": 39799, "LAT": null, "LON": null, "VMAX": null, "MSLP": null, "RMAX": null, "FSPD": null, "FDIR": null, "RENV": null, "PENV": null, "VALIDT": 0, "DTG": "2022-05-06 11:03:14", "LATNOW": null, "LONNOW": null, "WINDNOW": null, "DIRNOW": null, "SPDNOW": null, "TECH": "TRAK", "ADVNR": null, "ATCFID": null, "NAME": "PLACEHOLD", "FTECH": "NULL", "FCST_DTG": null, "RUN_DTG": "2022-05-06 11:05:58", "BASIN": null, "STMNR": null, "CAT_ID": null, "CAT_DESC": null, "MSGID": null, "VALIDTIME": "2022-05-06 11:00:00" }, "geometry": { "type": "Point", "coordinates": [ 114.89, -89.366 ] } }
]
}
